LICENSE.txt
MANIFEST.in
README.rst
setup.py
SimpleQW.egg-info/PKG-INFO
SimpleQW.egg-info/SOURCES.txt
SimpleQW.egg-info/dependency_links.txt
SimpleQW.egg-info/requires.txt
SimpleQW.egg-info/top_level.txt
SimpleQW.egg-info/zip-safe
src/.DS_Store
src/simpleqw/__init__.py
src/simpleqw/__init__.pyc
src/simpleqw/_finite_well.py
src/simpleqw/finite_well_1d.c
src/simpleqw/finite_well_1d.pyx
src/simpleqw/version.py
src/simpleqw/version.pyc
src/simpleqw/tests/__init__.py
src/simpleqw/tests/__init__.pyc
src/simpleqw/tests/test_finite_well_1d.py
src/simpleqw/tests/test_finite_well_1d.pyc