Metadata-Version: 1.0
Name: SimpleQW
Version: 0.1
Summary: simple quantum well computations
Home-page: http://scott-maddox.github.io/simpleqw
Author: Scott J. Maddox
Author-email: smaddox@utexas.edu
License: AGPLv3
Platform: UNKNOWN
